flet_audio_recorder/__init__.py
flet_audio_recorder/audio_recorder.py
flet_audio_recorder/types.py
flet_audio_recorder-0.80.5.dist-info/licenses/LICENSE
flutter/flet_audio_recorder/CHANGELOG.md
flutter/flet_audio_recorder/LICENSE
flutter/flet_audio_recorder/README.md
flutter/flet_audio_recorder/analysis_options.yaml
flutter/flet_audio_recorder/pubspec.lock
flutter/flet_audio_recorder/pubspec.yaml
flutter/flet_audio_recorder/lib/flet_audio_recorder.dart
flutter/flet_audio_recorder/lib/src/audio_recorder.dart
flutter/flet_audio_recorder/lib/src/extension.dart
flutter/flet_audio_recorder/lib/src/utils/audio_recorder.dart
flet_audio_recorder-0.80.5.dist-info/METADATA
flet_audio_recorder-0.80.5.dist-info/WHEEL
flet_audio_recorder-0.80.5.dist-info/top_level.txt
flet_audio_recorder-0.80.5.dist-info/RECORD
